UFC_Data_Scraper/__init__.py
UFC_Data_Scraper/helpers.py
UFC_Data_Scraper/scraper.py
UFC_Data_Scraper-1.0.0.dist-info/LICENSE
UFC_Data_Scraper-1.0.0.dist-info/METADATA
UFC_Data_Scraper-1.0.0.dist-info/WHEEL
UFC_Data_Scraper-1.0.0.dist-info/top_level.txt
UFC_Data_Scraper-1.0.0.dist-info/RECORD
