Metadata-Version: 2.1
Name: UFC-Data-Scraper
Version: 1.0.0
Summary: Packages uses BeautifulSoup API to scrape historical data from ufcstat.com
Home-page: https://github.com/kriegernathan1/UFC_Data_Scraper
Author: Nathan Krieger
Author-email: kriegerdevelopment@gmail.com
License: UNKNOWN
Platform: UNKNOWN
Classifier: Programming Language :: Python :: 3
Classifier: License :: OSI Approved :: MIT License
Classifier: Operating System :: OS Independent
Requires-Python: >=3.6
Requires-Dist: tqdm
Requires-Dist: requests
Requires-Dist: beautifulsoup4
